{
  "title": "Peanu's blog",
  "url": "http://localhost:8080/",
  "domain": "update-me.com",
  "description": "Description of the website. Update me.",
  "genre": "Insert a schema.org genre",
  "googleAnalyticsId": "GA ID. Update me. Note, that this is not compatible with the not-yet-commonly used version 4 of Google Analytics",
  "sendWebVitals": false,
  "feed": {
    "subtitle": "Subtitle. Update me.",
    "filename": "feed.xml",
    "path": "/feed/feed.xml",
    "id": "https://update-me.com"
  },
  "jsonfeed": {
    "path": "/feed/feed.json",
    "url": "https://update-me.com/feed/feed.json"
  },
  "author": {
    "name": "Peanu",
    "twitterHandle": ".",
    "avatarUrl": "/img/peanu.png",
    "intro": "你好，我是 Peanu。Peanu 這個名稱是來從「Peanut（花生）」而來的，因為我很喜歡花生。在接觸程式以前沒有對某樣事物抱持熱情，但現在既使花了一整天的時間來寫 code 也不會感到疲憊。目前擔任前端工程師，還在持續精進自己的能力，希望可以成為更好的工程師。"
  },
  "publisher": {
    "name": "Peanu"
  }
}
